statgram/__init__.py
statgram/core_requests.py
statgram/main.py
statgram/schemas.py
statgram-0.2.22.dist-info/LICENSE
statgram-0.2.22.dist-info/METADATA
statgram-0.2.22.dist-info/WHEEL
statgram-0.2.22.dist-info/top_level.txt
statgram-0.2.22.dist-info/RECORD
